jupyterlab_rmotr_solutions/__init__.py
jupyterlab_solutions-0.0.1.dist-info/LICENSE
jupyterlab_solutions-0.0.1.dist-info/METADATA
jupyterlab_solutions-0.0.1.dist-info/WHEEL
jupyterlab_solutions-0.0.1.dist-info/top_level.txt
jupyterlab_solutions-0.0.1.dist-info/RECORD
