Metadata-Version: 2.1
Name: jupyterlab-solutions
Version: 0.0.1
Summary: A jupyterlab extension to hide solutions for assignments
Home-page: UNKNOWN
Author: RMOTR
License: UNKNOWN
Platform: UNKNOWN
Requires-Dist: jupyterlab (>=0.35.4)
Requires-Dist: jupyter-nbextensions-configurator (>=0.4.0)
